{
  "kind": "collectionType",
  "collectionName": "tour_cards",
  "info": {
    "name": "tourCard",
    "description": ""
  },
  "options": {
    "increments": true,
    "timestamps": true,
    "draftAndPublish": true
  },
  "attributes": {
    "name": {
      "type": "string"
    },
    "sights": {
      "type": "string"
    },
    "audio": {
      "type": "string"
    },
    "languages": {
      "type": "string"
    },
    "duration": {
      "type": "string"
    },
    "description": {
      "type": "text"
    },
    "footerText": {
      "type": "string"
    },
    "picture": {
      "model": "file",
      "via": "related",
      "allowedTypes": [
        "images",
        "files",
        "videos"
      ],
      "plugin": "upload",
      "required": false
    },
    "icon": {
      "model": "file",
      "via": "related",
      "allowedTypes": [
        "images",
        "files",
        "videos"
      ],
      "plugin": "upload",
      "required": false
    },
    "price": {
      "type": "string"
    }
  }
}
